sense_monit_lib/__init__.py
sense_monit_lib/check_db_exist.py
sense_monit_lib/constants.py
sense_monit_lib/email_base.py
sense_monit_lib/models.py
sense_monit_lib/monit_send.py
sense_monit_lib/msg_base.py
sense_monit_lib/send_email.py
sense_monit_lib/send_email_base.py
sense_monit_lib/send_message.py
sense_monit_lib/send_msg_base.py
sense_monit_lib/share_interface.py
sense_monit_lib/utils.py
sense_monit_lib-0.2.6.dist-info/METADATA
sense_monit_lib-0.2.6.dist-info/WHEEL
sense_monit_lib-0.2.6.dist-info/top_level.txt
sense_monit_lib-0.2.6.dist-info/RECORD
