Metadata-Version: 2.1
Name: sense-monit-lib
Version: 0.2.6
Summary: sense monit
Home-page: UNKNOWN
Author: kafka0102
Author-email: yujianjia@sensedeal.ai
License: BSD License
Platform: UNKNOWN
Classifier: Environment :: Web Environment
Classifier: Framework :: Django
Classifier: Framework :: Django :: 2.1
Classifier: Intended Audience :: Developers
Classifier: License :: OSI Approved :: BSD License
Classifier: Operating System :: OS Independent
Classifier: Programming Language :: Python
Classifier: Programming Language :: Python :: 3.5
Classifier: Programming Language :: Python :: 3.6
Classifier: Topic :: Internet :: WWW/HTTP
Classifier: Topic :: Internet :: WWW/HTTP :: Dynamic Content
Requires-Dist: sense-core (>=0.1.1)
Requires-Dist: aliyunsdkcore (>=1.0.3)
